MapPlotter/MapPlotter.py
MapPlotter/__init__.py
MapPlotter-2.2.0.dist-info/LICENSE
MapPlotter-2.2.0.dist-info/METADATA
MapPlotter-2.2.0.dist-info/WHEEL
MapPlotter-2.2.0.dist-info/top_level.txt
MapPlotter-2.2.0.dist-info/RECORD
