Metadata-Version: 2.1
Name: MapPlotter
Version: 2.2.0
Summary: 2D map plots of data and NetCDF files using Cartopy
Home-page: https://github.com/ArnauMiro/MapPlotter
Author: Arnau Miro, Elena Terzić
Author-email: Arnau Miro <arnau.miro@upc.edu>, Elena Terzić <elena.terzic@proton.me>
Maintainer: Arnau Miro
Maintainer-email: Arnau Miro <arnau.miro@upc.edu>
License: GNU GENERAL PUBLIC LICENSE
Project-URL: Homepage, https://github.com/ArnauMiro/MapPlotter
Project-URL: Bug Reports, https://github.com/ArnauMiro/MapPlotter/issues
Project-URL: Source, https://github.com/ArnauMiro/MapPlotter
Keywords: cartopy,maps,plots
Classifier: Development Status :: 5 - Production/Stable
Classifier: Intended Audience :: Science/Research
Classifier: Topic :: Scientific/Engineering
Classifier: License :: OSI Approved :: GNU General Public License v3 (GPLv3)
Classifier: Programming Language :: Python :: 3
Classifier: Programming Language :: Python :: 3.7
Classifier: Programming Language :: Python :: 3.8
Classifier: Programming Language :: Python :: 3.9
Classifier: Programming Language :: Python :: 3.10
Classifier: Programming Language :: Python :: 3.11
Classifier: Programming Language :: Python :: 3 :: Only
Requires-Python: >=3.7
License-File: LICENSE
Requires-Dist: numpy
Requires-Dist: matplotlib
Requires-Dist: cartopy
Requires-Dist: cmocean
Requires-Dist: datetime
Requires-Dist: netCDF4
Requires-Dist: requests
Provides-Extra: full
